Metadata-Version: 2.1
Name: papermate
Version: 0.1.1
Summary: A Python package to help researchers and academics write papers using Markdown
Home-page: https://github.com/MartinHeroux/papermate
Author: Martin Héroux
Author-email: heroux.martin@gmail.com
License: MIT
Platform: UNKNOWN
Classifier: License :: OSI Approved :: MIT License
Classifier: Programming Language :: Python :: 3.8
Classifier: Operating System :: OS Independent
